sounava/__init__.py
sounava/__main__.py
sounava/ext.py
sounava-0.0.10.dist-info/licenses/LICENSE
sounava-0.0.10.dist-info/METADATA
sounava-0.0.10.dist-info/WHEEL
sounava-0.0.10.dist-info/top_level.txt
sounava-0.0.10.dist-info/RECORD
