Metadata-Version: 2.4
Name: sounava
Version: 0.0.10
Summary: A telegram SDK offering clean and simple route decorators.
Author: Ankit Mehta
Author-email: starexx.m@gmail.com
Classifier: Programming Language :: Python :: 3
Classifier: License :: OSI Approved :: MIT License
Classifier: Operating System :: OS Independent
Requires-Python: >=3.6
License-File: LICENSE
Dynamic: author
Dynamic: author-email
Dynamic: classifier
Dynamic: description
Dynamic: description-content-type
Dynamic: license-file
Dynamic: requires-python
Dynamic: summary
